
[
{"name": "Sean Abu Wilson",
"dob": "1985-02-06",
"birthplace": "Birmingham, AL",
"siblings" : 2,
"years_in_nyc": 8.4,
"favoritefood": "oatmeal raisin cookies"},
{‘name’: ‘Rebecca Chi-May Weng’,
‘dob’: ‘1996-05-17’,
‘birthplace’: ‘New York, NY’,
‘siblings’ : 0,
‘years_in_nyc’: 18,
‘favorite_food’: ‘Taiwanese beef noodle soup’},
{"name": "Charlie Schlinkert",
"dob": "1994-06-11",
"birthplace": "Darien, Ct",
"siblings" : 2,
"years_in_nyc": 7.2,
"favorite_food": "Hamburgers"},
{"name": "Clare Blessen",
"dob": "1994-08-10",
"birthplace": "Chicago, IL",
"siblings" : 1,
"years_in_nyc": 2,
"favorite_food": "cheese"},
{"name": "Dave Bletsch",
"dob": "1982-04-29",
"birthplace": "New Hyde Park, NY",
"siblings" : 2,
"years_in_nyc": .6,
"favorite_food": "buffalo wings"},
{"name": "Eddie Pognon",
"dob": "1994-04-26",
"birthplace": "Newark, New Jersey",
"siblings" : 4,
"years_in_nyc": 22,
"favorite_food": "pasta"},
{"name": "Findlay Bowditch",
"dob": "1992-08-22",
"birthplace": "White Plains, NY",
"siblings" : 2,
"years_in_nyc": 1,
"favorite_food": "BBQ"},
{"name": "Gabriel Seemann",
"dob": "1991-02-09",
"birthplace": "San Diego, CA,
"siblings" : 3,
"years_in_nyc": 2.2,
"favorite_food": "Falafel"},
{"name": "Garrett Keyes",
"dob": "1993-09-20",
"birthplace": "New York City, NY",
"siblings" : 0,
"years_in_nyc": 3.3,
"favorite_food": "lamb vindaloo"},
{"name": "Jake Cohen",
 "dob": "1995-02-12",
 "birthplace": "Philadelphia, PA",
 "siblings": 1,
 "years_in_nyc": 1.4,
 "favorite_food": "pizza"},
 {"name": "JP Rinfret",
"dob": "1990-08-02",
"birthplace": "Manhasset, NY",
"siblings" : 2,
"years_in_nyc": 5.6,
"favorite_food": "breaded chicken cutlets"},
{‘name’: ‘Kenny Miyasato’,
‘dob’: ‘1988-07-13’,
‘birthplace’: ‘Lima, Peru’,
‘siblings’ : 0,
‘years_in_nyc’: 0,
‘favorite_food’: ‘Pizza’},
{"name": "Kyle McNicoll",
"dob": "1994-02-11",
"birthplace": "NYC",
"siblings": 1,
"years_in_nyc": 24,
"favorite_food": "salmon sushi"},
{"name": "Marco Sanchez-Ayala",
"dob": "1996-04-11",
"birthplace": "Portland, OR",
"siblings" : 1,
"years_in_nyc": 1.3,
"favorite_food": "cinnamon rolls"},
Matt Finch 12:06 PM
{‘name’: ‘Matthew R Finch’,
‘dob’: ‘1992-03-13’,
‘birthplace’: ‘Detroit, MI’,
‘siblings’ : 1,
‘years_in_nyc’: 6,
‘favorite_food’: ‘green curry’},
{"name": "melissa",
             "dob": "December 4, 1987",
             "birthplace": "Seattle, WA",
             "siblings": 1,
             "years_in_nyc": 6.5,
             "favorite_food": "coffee"
},
{"name": "Michael Eby",
"dob": "1991-01-03",
"birthplace": "St. Louis, MO",
"siblings" : 1,
"years_in_nyc": 10,
"favorite_food": "sandwiches"},
{"name": "Ravi Charan",
"dob": "1992-07-07",
"birthplace": "Minneapolis, MN",
"siblings" : 2,
"years_in_nyc": 5.181022,
"favorite_food": "pandas"},
{‘name’: ‘Regina Ryan’,
‘dob’: ‘1991-10-08’,
‘birthplace’: ‘Tashkent, Uzbekistan’,
‘siblings’ : 1,
‘years_in_nyc’: 12.4,
‘favorite_food’: ‘noodles’},
{‘name’ : ‘Samuel Diaz’,
‘dob’ : ‘1987-09-21’,
‘birthplace’ : ‘Harlem, NY’,
‘siblings’ : 2,
‘years_in_nyc’: 32,
‘favorite_food’: ‘Grilled Steak with Rice and Broccoli’},
{‘name’: ‘Sasha Epelbaum’,
‘dob’: ‘1996-10-05’,
‘birthplace’: ‘NYC, NY’,
‘siblings’ : 1,
‘years_in_nyc’: 19,
‘favorite_food’: ‘nyc bagels’},
{‘name’: ‘Stephanie Bourdeau’,
‘dob’: ‘1993-09-30’,
‘birthplace’: ‘Brooklyn, NY’,
‘siblings’ : 2,
‘years_in_nyc’: 26.1,
‘favorite_food’: ‘NYC pizza’},
{"name": "Wesley Willis",
"dob": "1992-06-04",
"birthplace": "Detroit, MI",
"siblings" : 4,
"years_in_nyc": 7,
"favorite_food": "banana fritters"},
{‘name’: ‘Zoe Zhu’,
‘dob’: ‘1992-06-06’,
‘birthplace’: ‘Shanghai, China’,
‘siblings’ : 0,
‘years_in_nyc’: 1.5,
‘favorite_food’: ‘cinnamon toast crunch’},
{"name": "Christopher Shaw",
"dob": "1982-11-11",
"birthplace": "Baltimore, MD",
"siblings" : 0,
"years_in_nyc": 2.0,
"favorite_food": "Italian Sub"}

]
